airflow_snapshot_test/__init__.py
airflow_snapshot_test/airflow_suite.py
airflow_snapshot_test/snapshot.py
airflow_snapshot_test-0.1.10.dist-info/WHEEL
airflow_snapshot_test-0.1.10.dist-info/METADATA
airflow_snapshot_test-0.1.10.dist-info/RECORD
