Metadata-Version: 2.1
Name: airflow-snapshot-test
Version: 0.1.10
Summary: 
Author: komalkot
Author-email: komalkot@thoughtworks.com
Requires-Python: >=3.6,<4.0
Classifier: Programming Language :: Python :: 3
Classifier: Programming Language :: Python :: 3.6
Classifier: Programming Language :: Python :: 3.7
Classifier: Programming Language :: Python :: 3.8
Classifier: Programming Language :: Python :: 3.9
Requires-Dist: SQLAlchemy (>=1.3,<1.4)
Requires-Dist: apache-airflow (==1.10.15)
Requires-Dist: cattrs (==1.0.0)
Requires-Dist: presto-python-client (>=0.7.0,<0.8.0)
